{
    "allTransactionHistory": [
        {
            "transactionId": 16103,
            "userId": 12,
            "orderId": 15271,
            "credit": 0,
            "debit": 24,
            "dateTime": "26/09/2023 05:46 PM",
            "adminUserId": 0,
            "itemId": 52,
            "quantity": 1,
            "status": "delivered",
            "amount": 24,
            "adminUserName": "",
            "userName": "Shrikant Jaiswal",
            "nameHindi": "श्रीकांत जायसवाल",
            "walletAmount": 0,
            "itemName": "Idli Sambhar (2 Pcs)",
            "itemNameHindi": "इडली संभर (2 नग)"
        },
        {
            "transactionId": 16102,
            "userId": 12,
            "orderId": 15269,
            "credit": 0,
            "debit": 48,
            "dateTime": "26/09/2023 05:22 PM",
            "adminUserId": 0,
            "itemId": 52,
            "quantity": 2,
            "status": "delivered",
            "amount": 48,
            "adminUserName": "",
            "userName": "Shrikant Jaiswal",
            "nameHindi": "श्रीकांत जायसवाल",
            "walletAmount": 0,
            "itemName": "Idli Sambhar (2 Pcs)",
            "itemNameHindi": "इडली संभर (2 नग)"
        },
        {
            "transactionId": 16101,
            "userId": 12,
            "orderId": 15268,
            "credit": 0,
            "debit": 48,
            "dateTime": "26/09/2023 05:16 PM",
            "adminUserId": 0,
            "itemId": 52,
            "quantity": 2,
            "status": "delivered",
            "amount": 48,
            "adminUserName": "",
            "userName": "Shrikant Jaiswal",
            "nameHindi": "श्रीकांत जायसवाल",
            "walletAmount": 0,
            "itemName": "Idli Sambhar (2 Pcs)",
            "itemNameHindi": "इडली संभर (2 नग)"
        }
    ],
    "totalCredit": 0.0,
    "totalDebit": 120.0,
    "totalwallet": 0,
    "amount": -120.0
}